{
  "id": 589,
  "delay": 12,
  "primaryFrames": [
    241,
    241,
    295,
    295,
    346,
    346,
    38,
    38,
    88,
    88,
    143,
    143,
    143,
    143,
    88,
    88,
    38,
    38,
    346,
    346,
    295,
    295,
    241,
    241,
    81,
    81,
    133,
    133,
    188,
    188,
    243,
    243,
    298,
    298,
    349,
    349,
    349,
    349,
    298,
    298,
    243,
    243,
    188,
    188,
    133,
    133,
    81,
    81,
    154,
    154,
    154,
    154,
    208,
    261,
    261,
    261,
    315,
    261,
    261,
    208,
    208,
    154,
    154,
    154
  ],
  "secondaryFrames": [
    164,
    219,
    274,
    329,
    19,
    66,
    164,
    219,
    274,
    329,
    19,
    66,
    164,
    219,
    274,
    329,
    19,
    66,
    164,
    219,
    274,
    329,
    19,
    66,
    164,
    219,
    274,
    329,
    19,
    66,
    164,
    219,
    274,
    329,
    19,
    66,
    164,
    219,
    274,
    329,
    19,
    66,
    164,
    219,
    274,
    329,
    19,
    66,
    -1,
    -1,
    -1,
    -1,
    -1,
    -1,
    -1,
    -1,
    -1,
    -1,
    -1,
    -1,
    -1,
    -1,
    -1,
    -1
  ],
  "frameDelay": [
    0,
    0,
    0,
    0,
    0,
    0,
    0,
    0,
    0,
    0,
    0,
    0,
    0,
    0,
    0,
    0,
    0,
    0,
    0,
    0,
    0,
    0,
    0,
    0,
    0,
    0,
    0,
    0,
    0,
    0,
    0,
    0,
    0,
    0,
    0,
    0,
    0,
    0,
    0,
    0,
    0,
    0,
    0,
    0,
    0,
    0,
    0,
    0,
    0,
    0,
    0,
    0,
    0,
    0,
    0,
    0,
    0,
    0,
    0,
    0,
    0,
    0,
    0,
    0
  ]
}