{
  "id": 2851,
  "parent": 2851,
  "type": 0,
  "buttonType": 0,
  "contentType": 0,
  "width": 512,
  "height": 334,
  "hoverParentIndex": -1,
  "scrollHeight": 0,
  "hidden": false,
  "children": [
    2852,
    2853,
    2854,
    2855,
    2856,
    2857,
    2858,
    2859,
    2860,
    2861,
    2862,
    2863,
    2864,
    2865,
    2866,
    2867,
    2868,
    2869,
    2870,
    2871,
    2872,
    2873,
    2874,
    2875,
    2876,
    2877,
    2878,
    2879,
    2880,
    2881,
    2882,
    2883,
    2884,
    2885,
    2886,
    2887,
    2888,
    2889,
    2890,
    2891,
    2892,
    2893,
    2894,
    2895,
    2896,
    2897,
    2898,
    2899,
    2900,
    2901,
    2902,
    2903,
    2904,
    2905,
    2906,
    2907,
    2908,
    2909,
    2910,
    2911,
    2912,
    2913,
    2914,
    2915,
    2916,
    2917,
    2918,
    2919,
    2920,
    2921,
    2922,
    2923,
    2924,
    2925,
    2926,
    2927,
    2928,
    2929,
    2930,
    2931,
    2932,
    2933,
    2934,
    2935,
    2936,
    2937,
    2938,
    2939,
    2940,
    2941,
    2942,
    2943,
    2944,
    2945,
    2946,
    2947,
    2948,
    2949,
    2950,
    2951,
    2952,
    2953,
    2954,
    2955,
    2956,
    2957,
    2958,
    2959,
    2960,
    2961,
    2962,
    2963,
    2964,
    2965,
    2966,
    2967,
    2968,
    2969,
    2970,
    2971,
    2972,
    2973,
    2974,
    2975,
    2976,
    2977,
    2978,
    2979,
    2980,
    2981,
    2982,
    2983,
    2984,
    2985,
    2986,
    2987,
    2988,
    2989,
    2990,
    2991,
    2992,
    2993,
    2994,
    2995,
    2996,
    2997,
    2998,
    2999,
    3000,
    3001,
    3002,
    3003,
    3004,
    3005,
    3006,
    3007,
    3008,
    3009,
    3010,
    3011,
    3012,
    3013,
    3014,
    3015,
    3016,
    3017,
    3018,
    3019,
    3020,
    3021,
    3022
  ],
  "childX": [
    12,
    12,
    12,
    12,
    12,
    100,
    100,
    100,
    100,
    188,
    100,
    188,
    188,
    188,
    188,
    276,
    364,
    276,
    276,
    276,
    276,
    364,
    364,
    364,
    364,
    412,
    412,
    412,
    412,
    412,
    12,
    -3,
    -3,
    -3,
    -3,
    -3,
    -3,
    -3,
    479,
    479,
    479,
    479,
    479,
    479,
    479,
    73,
    109,
    145,
    181,
    217,
    253,
    289,
    325,
    361,
    397,
    433,
    72,
    108,
    144,
    180,
    216,
    252,
    288,
    324,
    360,
    396,
    432,
    252,
    37,
    37,
    12,
    475,
    439,
    475,
    439,
    288,
    324,
    360,
    396,
    432,
    459,
    216,
    180,
    144,
    108,
    72,
    36,
    17,
    420,
    154,
    59,
    60,
    85,
    110,
    135,
    160,
    185,
    210,
    235,
    260,
    285,
    310,
    335,
    360,
    385,
    410,
    435,
    197,
    59,
    84,
    109,
    134,
    160,
    185,
    210,
    235,
    260,
    285,
    310,
    335,
    360,
    385,
    410,
    435,
    208,
    207,
    220,
    50,
    114,
    176,
    240,
    302,
    358,
    420,
    50,
    114,
    176,
    240,
    302,
    358,
    50,
    114,
    176,
    240,
    302,
    358,
    420,
    50,
    114,
    176,
    240,
    302,
    358,
    113,
    175,
    239,
    301,
    357,
    53,
    117,
    179,
    243,
    305,
    361,
    422,
    52,
    116,
    178,
    242,
    304,
    360
  ],
  "childY": [
    20,
    80,
    140,
    200,
    260,
    20,
    80,
    140,
    200,
    20,
    260,
    80,
    140,
    200,
    260,
    20,
    80,
    80,
    140,
    200,
    260,
    140,
    20,
    200,
    260,
    20,
    80,
    140,
    200,
    260,
    20,
    49,
    85,
    121,
    157,
    193,
    229,
    265,
    50,
    86,
    122,
    158,
    194,
    230,
    266,
    299,
    299,
    299,
    299,
    299,
    299,
    299,
    299,
    299,
    299,
    299,
    5,
    5,
    5,
    5,
    5,
    5,
    5,
    5,
    5,
    5,
    5,
    34,
    5,
    299,
    290,
    20,
    5,
    290,
    299,
    34,
    34,
    34,
    34,
    34,
    34,
    34,
    34,
    34,
    34,
    34,
    34,
    34,
    29,
    30,
    249,
    250,
    250,
    250,
    250,
    250,
    250,
    250,
    250,
    250,
    250,
    250,
    250,
    250,
    250,
    250,
    250,
    289,
    250,
    250,
    250,
    250,
    250,
    250,
    250,
    250,
    250,
    250,
    250,
    250,
    250,
    250,
    250,
    250,
    64,
    148,
    225,
    185,
    185,
    185,
    185,
    185,
    185,
    185,
    265,
    265,
    265,
    265,
    265,
    265,
    185,
    185,
    185,
    185,
    185,
    185,
    185,
    265,
    265,
    265,
    265,
    265,
    265,
    185,
    185,
    185,
    185,
    185,
    100,
    100,
    100,
    100,
    100,
    100,
    100,
    180,
    180,
    180,
    180,
    180,
    180
  ]
}