{
  "id": 5859,
  "parent": 5855,
  "type": 0,
  "buttonType": 0,
  "contentType": 0,
  "width": 145,
  "height": 190,
  "hoverParentIndex": -1,
  "scrollHeight": 0,
  "hidden": false,
  "children": [
    5860,
    5861,
    5862,
    5863,
    5864,
    5865,
    5866,
    5867,
    5868,
    5869,
    5870,
    5871
  ],
  "childX": [
    5,
    5,
    5,
    22,
    21,
    22,
    78,
    78,
    78,
    78,
    78,
    78
  ],
  "childY": [
    5,
    97,
    51,
    11,
    57,
    103,
    5,
    51,
    97,
    18,
    64,
    110
  ]
}