{
  "id": 1101,
  "description": "A series of connected metal rings.",
  "value": 210,
  "modelIndex": 2558,
  "iconY": 2,
  "iconZoom": 1100,
  "iconCameraPitch": 568,
  "options": [
    null,
    "Wear"
  ],
  "maleModel0": 301,
  "maleOffsetY": 0,
  "femaleModel0": 464,
  "femaleOffsetY": 0,
  "oldColors": [
    61
  ],
  "newColors": [
    33
  ],
  "name": "Iron chainbody",
  "notedId": 1102,
  "wearBonus": {
    "amagic": -15,
    "dstab": 10,
    "dslash": 15,
    "dcrush": 19,
    "dmagic": -3,
    "drange": 12
  },
  "wearSlot": "body",
  "weight": 6.803,
  "tradeable": true
}